amd/__init__.py
amd/__main__.py
amd/app/__init__.py
amd/app/app.py
amd/data/__init__.py
amd/data/bookmarks.py
amd/data/config.py
amd/data/data_directory.py
amd/data/history.py
amd/dialogs/__init__.py
amd/dialogs/error.py
amd/dialogs/help_dialog.py
amd/dialogs/information.py
amd/dialogs/input_dialog.py
amd/dialogs/text_dialog.py
amd/dialogs/yes_no_dialog.py
amd/screens/__init__.py
amd/screens/main.py
amd/utility/__init__.py
amd/utility/advertising.py
amd/utility/forge.py
amd/utility/type_tests.py
amd/widgets/__init__.py
amd/widgets/navigation.py
amd/widgets/omnibox.py
amd/widgets/viewer.py
amd/widgets/navigation_panes/__init__.py
amd/widgets/navigation_panes/bookmarks.py
amd/widgets/navigation_panes/history.py
amd/widgets/navigation_panes/local_files.py
amd/widgets/navigation_panes/navigation_pane.py
amd/widgets/navigation_panes/table_of_contents.py
amdreader-0.9.7.dist-info/licenses/LICENSE
amdreader-0.9.7.dist-info/METADATA
amdreader-0.9.7.dist-info/WHEEL
amdreader-0.9.7.dist-info/entry_points.txt
amdreader-0.9.7.dist-info/top_level.txt
amdreader-0.9.7.dist-info/RECORD
