Metadata-Version: 2.4
Name: amdreader
Version: 0.9.7
Summary: A Markdown document viewer for the terminal.
Author-email: Eivind Teig <eivind.teig@gmail.com>, Dave Pearson <dave@textualize.io>
License-Expression: MIT
Project-URL: homepage, https://github.com/eivl/amdreader
Classifier: Development Status :: 4 - Beta
Classifier: Environment :: Console
Classifier: Intended Audience :: Developers
Classifier: Intended Audience :: End Users/Desktop
Classifier: Intended Audience :: Information Technology
Classifier: Intended Audience :: Other Audience
Classifier: Operating System :: MacOS
Classifier: Operating System :: Microsoft :: Windows :: Windows 10
Classifier: Operating System :: Microsoft :: Windows :: Windows 11
Classifier: Operating System :: POSIX :: Linux
Classifier: Programming Language :: Python :: 3.10
Classifier: Programming Language :: Python :: 3.11
Classifier: Programming Language :: Python :: 3.12
Classifier: Programming Language :: Python :: 3.13
Classifier: Programming Language :: Python :: 3.14
Classifier: Topic :: Software Development :: Documentation
Classifier: Topic :: Text Processing :: Markup :: Markdown
Requires-Python: >=3.10.0
License-File: LICENSE
Requires-Dist: httpcore>=1.0.9
Requires-Dist: httpx>=0.28.1
Requires-Dist: textual>=7.3.0
Requires-Dist: xdg>=6.0.0
Dynamic: license-file
